{
	"resource_pack_name": "Adventure Expansion",
	"texture_name": "atlas.items",
	"texture_data": {
		"stalwart_rock": {
			"textures": "textures/items/stalwart_rock"
		},
		"stalwart_hammer": {
			"textures": "textures/items/stalwart_hammer"
		},
		"adventure_expansion_spawn_egg": {
			"textures": [
				"textures/items/egg_revenant",
				"textures/items/egg_crumbles",
				"textures/items/egg_sailorager",
				"textures/items/egg_flupper",
				"textures/items/egg_sky_dragon",
				"textures/items/egg_inhabitant",
				"textures/items/egg_goose",
				"textures/items/egg_deepfish"
			]
		},
		"bottled_soul": {
			"textures": "textures/items/bottled_soul"
		},
		"blowpipe": {
			"textures": "textures/items/blowpipe"
		},
		"flintlock": {
			"textures": "textures/items/flintlock"
		},
		"cactus_spine": {
			"textures": "textures/items/cactus_spine"
		},
		"vine_staff": {
			"textures": "textures/items/vine_staff"
		},
		"sweet_bread": {
			"textures": "textures/items/sweet_bread"
		},
		"goose_egg": {
			"textures": "textures/items/goose_egg"
		},
		"goose_feather": {
			"textures": "textures/items/goose_feather"
		},
		"dart": {
			"textures": "textures/items/dart"
		}
	}
}